<?xml version="1.0" encoding="utf-8"?>
<!DOCTYPE hibernate-mapping PUBLIC "-//Hibernate/Hibernate Mapping DTD 3.0//EN"
"http://hibernate.sourceforge.net/hibernate-mapping-3.0.dtd">
<!-- 
    Mapping file autogenerated by MyEclipse Persistence Tools
-->
<hibernate-mapping>
    <class name="com.mucCollege.model.Course" table="course" catalog="java_test">
        <id name="courseid" type="java.lang.Integer">
            <column name="courseid" />
            <generator class="increment"></generator>
        </id>
        <property name="coursename" type="java.lang.String">
            <column name="coursename" length="20">
                <comment>课程名称</comment>
            </column>
        </property>
        <property name="detail" type="java.lang.String">
            <column name="detail" length="30">
                <comment>课程介绍</comment>
            </column>
        </property>
        <set name="selectcourses" inverse="true">
            <key>
                <column name="course">
                    <comment>所选课程</comment>
                </column>
            </key>
            <one-to-many class="com.mucCollege.model.Selectcourse" />
        </set>
        <set name="selectcourses_1" inverse="true">
            <key>
                <column name="course">
                    <comment>所选课程</comment>
                </column>
            </key>
            <one-to-many class="com.mucCollege.model.Selectcourse" />
        </set>
        <set name="teacourses" inverse="true">
            <key>
                <column name="course">
                    <comment>课程</comment>
                </column>
            </key>
            <one-to-many class="com.mucCollege.model.Teacourse" />
        </set>
        <set name="teacourses_1" inverse="true">
            <key>
                <column name="course">
                    <comment>课程</comment>
                </column>
            </key>
            <one-to-many class="com.mucCollege.model.Teacourse" />
        </set>
    </class>
</hibernate-mapping>
